odoo9_addon_website_event_filter_selector-9.0.1.0.0-py2.7-nspkg.pth
odoo_addons/website_event_filter_selector/__openerp__.py
odoo_addons/website_event_filter_selector/__init__.py
odoo_addons/website_event_filter_selector/README.rst
odoo_addons/website_event_filter_selector/models/__init__.py
odoo_addons/website_event_filter_selector/models/event.py
odoo_addons/website_event_filter_selector/templates/assets.xml
odoo_addons/website_event_filter_selector/templates/event.xml
odoo_addons/website_event_filter_selector/i18n/es.po
odoo_addons/website_event_filter_selector/i18n/de.po
odoo_addons/website_event_filter_selector/controllers/main.py
odoo_addons/website_event_filter_selector/controllers/__init__.py
odoo_addons/website_event_filter_selector/tests/__init__.py
odoo_addons/website_event_filter_selector/tests/test_ui.py
odoo_addons/website_event_filter_selector/demo/assets.xml
odoo_addons/website_event_filter_selector/images/choose.png
odoo_addons/website_event_filter_selector/images/all.png
odoo_addons/website_event_filter_selector/static/description/icon.png
odoo_addons/website_event_filter_selector/static/src/js/website_event_filter_selector.tour.js
odoo_addons/website_event_filter_selector/static/src/js/website_event_filter_selector.js
odoo9_addon_website_event_filter_selector-9.0.1.0.0.dist-info/top_level.txt
odoo9_addon_website_event_filter_selector-9.0.1.0.0.dist-info/WHEEL
odoo9_addon_website_event_filter_selector-9.0.1.0.0.dist-info/RECORD
odoo9_addon_website_event_filter_selector-9.0.1.0.0.dist-info/metadata.json
odoo9_addon_website_event_filter_selector-9.0.1.0.0.dist-info/DESCRIPTION.rst
odoo9_addon_website_event_filter_selector-9.0.1.0.0.dist-info/METADATA
odoo9_addon_website_event_filter_selector-9.0.1.0.0.dist-info/namespace_packages.txt
