Metadata-Version: 2.0
Name: odoo9-addon-website-event-filter-selector
Version: 9.0.1.0.0
Summary: Add a customizable top area to filter events with selectors
Home-page: https://www.tecnativa.com
Author: Antiun Ingeniería S.L., Tecnativa, Odoo Community Association (OCA)
Author-email: support@odoo-community.org
License: LGPL-3
Platform: UNKNOWN
Requires-Dist: odoo (<9.1a,>=9.0a)
Classifier: Programming Language :: Python :: 2.7
Classifier: Framework :: Odoo
Classifier: License :: OSI Approved :: GNU Lesser General Public License v3 (LGPLv3)
